edunn/__init__.py
edunn/initializers.py
edunn/metrics.py
edunn/model.py
edunn/optimizer.py
edunn/plot.py
edunn/datasets/__init__.py
edunn/datasets/classification.py
edunn/datasets/regression.py
edunn/datasets/classification_data/iris.csv
edunn/datasets/classification_data/study1d.csv
edunn/datasets/classification_data/study2d.csv
edunn/datasets/classification_data/study2d_easy.csv
edunn/datasets/regression_data/boston_housing.csv
edunn/datasets/regression_data/insurance.csv
edunn/datasets/regression_data/real_state.csv
edunn/datasets/regression_data/study1d.csv
edunn/datasets/regression_data/study2d.csv
edunn/datasets/regression_data/wine_red.csv
edunn/datasets/regression_data/wine_white.csv
edunn/models/__init__.py
edunn/models/activations.py
edunn/models/bias.py
edunn/models/binary_cross_entropy_error.py
edunn/models/cross_entropy_error.py
edunn/models/dense.py
edunn/models/fake.py
edunn/models/linear.py
edunn/models/linear_regression.py
edunn/models/logistic_regression.py
edunn/models/mean_error.py
edunn/models/sequential.py
edunn/models/squared_error.py
edunn/utils/__init__.py
edunn/utils/check_gradient.py
edunn/utils/comparisons.py
edunn/utils/model2function.py
edunn/utils/numerical_gradient.py
edunn-0.1.6.dist-info/LICENSE
edunn-0.1.6.dist-info/METADATA
edunn-0.1.6.dist-info/WHEEL
edunn-0.1.6.dist-info/top_level.txt
edunn-0.1.6.dist-info/RECORD
