Metadata-Version: 2.1
Name: edunn
Version: 0.1.6
Summary: An educational implementation of a Keras-like neural network framework. 
Home-page: https://github.com/facundoq/edunn
Author: Facundo Quiroga
Author-email: fquiroga@lidi.info.unlp.edu.ar
License: GNU Affero General Public License v3 or later (AGPLv3+)
Project-URL: Bug Tracker, https://github.com/facundoq/edunn/issues
Project-URL: Documentation, https://github.com/facundoq/edunn
Project-URL: Source Code, https://github.com/facundoq/edunn
Platform: UNKNOWN
Classifier: Programming Language :: Python
Classifier: Programming Language :: Python :: 3
Classifier: Programming Language :: Python :: 3.6
Classifier: Programming Language :: Python :: Implementation :: CPython
Classifier: License :: OSI Approved :: Python Software Foundation License
Classifier: License :: OSI Approved :: GNU Affero General Public License v3 or later (AGPLv3+)
Requires-Python: >=3.6.0
Requires-Dist: colorama
Requires-Dist: matplotlib
Requires-Dist: numpy
Requires-Dist: tqdm
